{"results":[{"sample":"sample-66","action":"moving","confidence":0.85},{"sample":"sample-67","action":"moving","confidence":0.85},{"sample":"sample-68","action":"moving","confidence":0.5},{"sample":"sample-69","action":"moving","confidence":0.8},{"sample":"sample-70","action":"eating_prey","confidence":0.92},{"sample":"sample-71","action":"moving","confidence":0.8},{"sample":"sample-72","action":"moving","confidence":0.8},{"sample":"sample-73","action":"moving","confidence":0.65},{"sample":"sample-74","action":"moving","confidence":0.8},{"sample":"sample-75","action":"moving","confidence":0.75},{"sample":"sample-76","action":"eating_paste","confidence":0.92},{"sample":"sample-77","action":"moving","confidence":0.82},{"sample":"sample-78","action":"moving","confidence":0.7}]}